{
  "ret": true,
  "data": {
    "city": "深圳",
    "swiperList": [{
      "id": "0001",
      "imgUrl":"http://mp-piao-admincp.qunarzz.com/mp_piao_admin_mp_piao_admin/admin/20199/249dfa53de67b8824a96f9821e58f30d.jpg_750x200_48bf24d9.jpg"
    },{
      "id": "0002",
      "imgUrl":"http://mp-piao-admincp.qunarzz.com/mp_piao_admin_mp_piao_admin/admin/20199/47f7d9e9fb7c5cb88a1245180c9ca5b4.jpg_750x200_de4858e1.jpg"
    },{
      "id": "0003",
      "imgUrl":"http://mp-piao-admincp.qunarzz.com/mp_piao_admin_mp_piao_admin/admin/20193/b23a39921e8b78f38b61412d691d93ea.jpg_750x200_942ed7bd.jpg"
    },{
      "id": "0004",
      "imgUrl":"http://mp-piao-admincp.qunarzz.com/mp_piao_admin_mp_piao_admin/admin/20199/0fa39f9f5e66189e85b5c6e54278587d.jpg_750x200_86c8f2d8.jpg"
    }],
    "iconList": [{
      "id": "0001",
      "imgUrl": "http://img1.qunarzz.com/piao/fusion/1803/95/f3dd6c383aeb3b02.png",
      "text": "景点门票"
    },{
      "id": "0002",
      "imgUrl": "http://mp-piao-admincp.qunarzz.com/mp_piao_admin_mp_piao_admin/admin/20195/b0026eb6f96fd2daecba0d7982c7e4c8.png",
      "text": "国庆特惠"
    },{
      "id": "0003",
      "imgUrl": "http://img1.qunarzz.com/piao/fusion/1804/ff/fdf170ee89594b02.png",
      "text": "深圳必游"
    },{
      "id": "0004",
      "imgUrl": "http://img1.qunarzz.com/piao/fusion/1803/50/26ffa31b56646402.png",
      "text": "海洋馆"
    },{
      "id": "0005",
      "imgUrl": "http://img1.qunarzz.com/piao/fusion/1803/4d/a1eda1a2b8414302.png",
      "text": "夜场狂欢"
    },
    {
      "id": "0006",
      "imgUrl": "http://mp-piao-admincp.qunarzz.com/mp_piao_admin_mp_piao_admin/admin/20194/cba147cf6cfcea7109d0bff6aac6f626.png",
      "text": "深圳动物园"
    },{
      "id": "0007",
      "imgUrl": "http://img1.qunarzz.com/piao/fusion/1803/a6/6d97515091789602.png",
      "text": "世界之窗"
    },{
      "id": "0008",
      "imgUrl": "http://img1.qunarzz.com/piao/fusion/1803/b6/37560ece9c62b502.png",
      "text": "东部华侨城"
    },{
      "id": "0009",
      "imgUrl": "http://img1.qunarzz.com/piao/fusion/1804/5a/13ceb38dcf262f02.png",
      "text": "一日游"
    },{
      "id": "0010",
      "imgUrl": "http://img1.qunarzz.com/piao/fusion/1803/b1/528a9e80403b8c02.png",
      "text": "玩转长隆"
    }],
    "recommendList": [{
      "id": "0001",
      "imgUrl":"http://img1.qunarzz.com/sight/p0/1909/7c/7c6a137effe1d34ea3.water.jpg_200x200_b4936d7d.jpg",
      "title": "东部华侨城大侠谷",
      "text": "峡谷中的刺激游乐园~玩的就是心跳！"
     },
     {
      "id": "0002",
      "imgUrl":"http://img1.qunarzz.com/sight/p0/1603/9d/9d8c0e9a01bba92e90.water.jpg_200x200_86f2e623.jpg",
      "title": "锦绣中华",
      "text": "一步迈进历史，一天游遍中华"
     },
     {
      "id": "0003",
      "imgUrl":"http://img1.qunarzz.com/sight/p0/1907/79/79e4ff041bd3d2a3a3.water.jpg_200x200_95356ed7.jpg",
      "title": "深圳欢乐谷",
      "text": "玛雅水公园，夏日玩水好去处"
     },
     {
      "id": "0004",
      "imgUrl":"http://img1.qunarzz.com/sight/p0/201303/04/3dc3e87356026a63c8d65eac.jpg_200x200_1de448b6.jpg",
      "title": "阿尔卑斯山滑雪谷",
      "text": "体会滑雪快感，嬉雪、观雪的绝佳去处"
     },
     {
      "id": "0005",
      "imgUrl":"http://img1.qunarzz.com/sight/p0/1412/6f/5d803c45af314b68f4652362fca42d11.water.jpg_200x200_42a7956b.jpg",
      "title": "青青世界",
      "text": "融入大自然、体会田园之乐"
     }],
    "weekendList": [{
      "id": "0001",
      "imgUrl": "http://img1.qunarzz.com/sight/source/1507/d9/2ddc7652fdba16.jpg_r_640x214_5e62f1a3.jpg",
      "title":"深圳周边游",
      "text": "远离城市拥堵，去周边开启清新假期吧。"
     },
     {
      "id": "0002",
      "imgUrl": "http://img1.qunarzz.com/sight/source/1811/15/66f14e0fd6fbb.jpg_r_640x214_5d69f21d.jpg",
      "title":"清远周边逛",
      "text": "人人都有一双发现美的眼睛，身边的事物最熟悉不过，那你可曾发现了被人遗漏的美？"
     },
     {
      "id": "0003",
      "imgUrl": "http://img1.qunarzz.com/sight/source/1811/b8/5d599bbdcf8b57.jpg_r_640x214_2ee055e3.jpg",
      "title":"深圳欢乐谷",
      "text": "玛雅水公园，夏日玩水好去处"
     },
     {
      "id": "0004",
      "imgUrl": "http://img1.qunarzz.com/sight/source/1602/88/bf120edeaea383.jpg_r_640x214_f8591f7b.jpg",
      "title":"欢乐长隆",
      "text": "世界欢乐汇聚长隆，这里拥有多个大型游乐设备和精彩的演出，和小伙伴们一起感受刺激的体验"
     }]
  }
}